MANIFEST.in
NEWS.txt
README.rst
setup.py
src/setr/__init__.py
src/setr/setr.py
src/setr.egg-info/PKG-INFO
src/setr.egg-info/SOURCES.txt
src/setr.egg-info/dependency_links.txt
src/setr.egg-info/entry_points.txt
src/setr.egg-info/not-zip-safe
src/setr.egg-info/top_level.txt