Metadata-Version: 1.1
Name: setr
Version: 0.1
Summary: Search for ExtraTerrestrial Ranges
Home-page: https://github.com/zachaysan/setr
Author: Zach Aysan
Author-email: zachaysan@gmail.com
License: MIT
Keywords: Ranges,Speed
Platform: UNKNOWN
Classifier: Development Status :: 2 - Pre-Alpha
Classifier: Intended Audience :: Developers
Classifier: License :: OSI Approved :: MIT License
Classifier: License :: OSI Approved :: W3C License
Classifier: License :: OSI Approved :: European Union Public Licence 1.1 (EUPL 1.1)
Classifier: License :: OSI Approved :: BSD License
Classifier: Programming Language :: Python :: 2
